llm_cohere/__init__.py
llm_cohere-1.0.dist-info/METADATA
llm_cohere-1.0.dist-info/WHEEL
llm_cohere-1.0.dist-info/entry_points.txt
llm_cohere-1.0.dist-info/top_level.txt
llm_cohere-1.0.dist-info/RECORD
