Metadata-Version: 2.1
Name: llm-cohere
Version: 1.0
Summary: Plugin for LLM adding support for Cohere's Generate and Summarize models
Home-page: https://github.com/accudio/llm-cohere
Author: Alistair Shepherd
License: Apache License, Version 2.0
Project-URL: Issues, https://github.com/accudio/llm-cohere/issues
Project-URL: CI, https://github.com/accudio/llm-cohere/actions
Project-URL: Changelog, https://github.com/accudio/llm-cohere/releases
Classifier: License :: OSI Approved :: Apache Software License
Requires-Python: >=3.9
Requires-Dist: llm (>=0.5)
Requires-Dist: cohere
Requires-Dist: fastavro (==1.8.2)
Provides-Extra: test
Requires-Dist: pytest ; extra == 'test'
Requires-Dist: pytest-asyncio ; extra == 'test'
